pyqt_top_titlebar_widget/__init__.py
pyqt_top_titlebar_widget/topTitleBarWidget.py
pyqt_top_titlebar_widget-0.0.21.dist-info/LICENSE
pyqt_top_titlebar_widget-0.0.21.dist-info/METADATA
pyqt_top_titlebar_widget-0.0.21.dist-info/WHEEL
pyqt_top_titlebar_widget-0.0.21.dist-info/top_level.txt
pyqt_top_titlebar_widget-0.0.21.dist-info/RECORD
