Metadata-Version: 2.1
Name: pyqt-top-titlebar-widget
Version: 0.0.21
Summary: PyQt top title bar widget for frameless window
Home-page: https://github.com/yjg30737/pyqt-top-titlebar-widget.git
Author: Jung Gyu Yoon
Author-email: yjg30737@gmail.com
License: MIT
License-File: LICENSE
Requires-Dist: PyQt5 (>=5.15)
Requires-Dist: pyqt-svg-icon-text-widget (>=0.0.1)
